{"cameraMode":{"drawMode":0,"name":"Shaded","section":"Shading Mode"},"sceneLighting":true,"audioPlay":false,"sceneViewState":{"m_AlwaysRefresh":false,"showFog":true,"showSkybox":true,"showFlares":true,"showImageEffects":true,"showParticleSystems":true,"showVisualEffectGraphs":true,"m_FxEnabled":true},"in2DMode":false,"pivot":{"x":-10.867216110229493,"y":-7.247377395629883,"z":-80.26225280761719},"rotation":{"x":0.7071068286895752,"y":0.0,"z":0.0,"w":0.7071068286895752},"size":112.56304931640625,"orthographic":false}